{
  "id": "e01-t15-readme",
  "name": "e01-t15-readme",
  "title": "E01-T15 README raiz del monorepo",
  "description": "comandos, mapa de apps/packages, como correr checks",
  "status": "planning",
  "dev_type": null,
  "scope": null,
  "package": null,
  "priority": "P1",
  "creator": "Andres",
  "assignee": "andres",
  "createdAt": "2026-07-03",
  "completedAt": null,
  "branch": null,
  "base_branch": "master",
  "worktree_path": null,
  "commit": null,
  "pr_url": null,
  "subtasks": [],
  "children": [],
  "parent": "07-03-epic-01-monorepo-setup",
  "relatedFiles": [],
  "notes": "",
  "meta": {}
}
